dmsuite/__init__.py
dmsuite/_version.py
dmsuite/cheb_bc.py
dmsuite/examples.py
dmsuite/interp.py
dmsuite/poly_diff.py
dmsuite/py.typed
dmsuite-0.3.0.dist-info/LICENSE
dmsuite-0.3.0.dist-info/METADATA
dmsuite-0.3.0.dist-info/WHEEL
dmsuite-0.3.0.dist-info/top_level.txt
dmsuite-0.3.0.dist-info/RECORD
