Metadata-Version: 2.1
Name: dmsuite
Version: 0.3.0
Summary: Differentiation matrices
Author: Stéphane Labrosse
Author-email: Adrien Morison <adrien.morison@gmail.com>
Maintainer: Stéphane Labrosse
Maintainer-email: Adrien Morison <adrien.morison@gmail.com>
License: GNU GENERAL PUBLIC LICENSE
Project-URL: homepage, https://github.com/labrosse/dmsuite
Classifier: Development Status :: 3 - Alpha
Classifier: Intended Audience :: Science/Research
Classifier: License :: OSI Approved :: GNU General Public License v2 (GPLv2)
Classifier: Programming Language :: Python :: 3 :: Only
Classifier: Programming Language :: Python :: 3.8
Classifier: Programming Language :: Python :: 3.9
Classifier: Programming Language :: Python :: 3.10
Classifier: Programming Language :: Python :: 3.11
Requires-Python: >=3.8
License-File: LICENSE
Requires-Dist: numpy (>=1.21)
Requires-Dist: scipy (>=1.6)
